src/__init__.py
src/ai/__init__.py
src/ai/ai_integration.py
src/ai/function_schemas.py
src/ai/prompt_templates.txt
src/ai/prompts.py
src/cli/__init__.py
src/cli/cli.py
src/core/__init__.py
src/core/core.py
src/core/search.py
src/utils/__init__.py
src/utils/backup.py
src/utils/move_manager.py
src/utils/undo_expiry.py
src/utils/undo_manager.py
src/utils/utils.py
folderly-1.0.5.dist-info/entry_points.txt
folderly-1.0.5.dist-info/METADATA
folderly-1.0.5.dist-info/WHEEL
folderly-1.0.5.dist-info/RECORD
