Metadata-Version: 2.3
Name: folderly
Version: 1.0.5
Summary: Smart Desktop File Management with AI Integration - Enhanced Path Display & Error-Free Operations
Author: Folderly Team
Author-email: aayush@aayussh.com
Requires-Python: >=3.8.1,<4.0.0
Classifier: Development Status :: 5 - Production/Stable
Classifier: Intended Audience :: Developers
Classifier: Intended Audience :: End Users/Desktop
Classifier: License :: OSI Approved :: MIT License
Classifier: Operating System :: OS Independent
Classifier: Programming Language :: Python :: 3
Classifier: Programming Language :: Python :: 3.9
Classifier: Programming Language :: Python :: 3.10
Classifier: Programming Language :: Python :: 3.11
Classifier: Programming Language :: Python :: 3.12
Classifier: Programming Language :: Python :: 3.13
Classifier: Topic :: Desktop Environment
Classifier: Topic :: System :: Filesystems
Classifier: Topic :: Utilities
Requires-Dist: openai (>=1.0.0,<2.0.0)
Requires-Dist: python-dotenv (>=1.0.0,<2.0.0)
Requires-Dist: send2trash (>=1.8.0,<2.0.0)
